[
    {
        "key": "NODE_ENV",
        "value": "production",
        "label": "{{serviceName}}",
        "content_type": "",
        "tags": {}
    },
    {
        "key": "APPINSIGHTS_CLOUDROLE",
        "value": "{{serviceName}}",
        "label": "{{serviceName}}",
        "content_type": "",
        "tags": {}
    },
    {
        "key": "CALCULATION_QUEUE_ADDRESS",
        "value": "ffc-demo-calculation",
        "label": "{{serviceName}}",
        "content_type": "",
        "tags": {}
    },
    {
        "key": "PAYMENT_TOPIC_ADDRESS",
        "value": "ffc-demo-payment",
        "label": "{{serviceName}}",
        "content_type": "",
        "tags": {}
    },
    {
        "key": "MESSAGE_QUEUE_HOST",
        "value": "SNDADPINFSB3401.servicebus.windows.net",
        "label": "{{serviceName}}",
        "content_type": "",
        "tags": {}
    },
    {
        "key": "PROTECTIVE_MONITORING_URL",
        "value": "",
        "label": "{{serviceName}}",
        "content_type": "",
        "tags": {}
    }
]